LICENSE
README.md
pyproject.toml
deepseek_ocr/__init__.py
deepseek_ocr/batch.py
deepseek_ocr/client.py
deepseek_ocr/config.py
deepseek_ocr/enums.py
deepseek_ocr/exceptions.py
deepseek_ocr/vlm_client.py
many_ocr_sdk.egg-info/PKG-INFO
many_ocr_sdk.egg-info/SOURCES.txt
many_ocr_sdk.egg-info/dependency_links.txt
many_ocr_sdk.egg-info/requires.txt
many_ocr_sdk.egg-info/top_level.txt
tests/test_client.py
tests/test_config.py
tests/test_enums.py
tests/test_exceptions.py
tests/test_rate_limiting.py
tests/test_vlm.py