Metadata-Version: 2.4
Name: many-ocr-sdk
Version: 0.4.0
Summary: A simple and efficient Python SDK for DeepSeek-OCR API
Author-email: whitewatercn <whitewatercn@outlook.com>
License-Expression: MIT
Project-URL: Homepage, https://github.com/BukeLy/DeepSeek-OCR-SDK
Project-URL: Documentation, https://github.com/BukeLy/DeepSeek-OCR-SDK#readme
Project-URL: Repository, https://github.com/BukeLy/DeepSeek-OCR-SDK
Project-URL: Issues, https://github.com/BukeLy/DeepSeek-OCR-SDK/issues
Keywords: ocr,deepseek,document-processing,pdf,image-to-text
Classifier: Development Status :: 4 - Beta
Classifier: Intended Audience :: Developers
Classifier: Programming Language :: Python :: 3
Classifier: Programming Language :: Python :: 3.10
Classifier: Programming Language :: Python :: 3.11
Classifier: Programming Language :: Python :: 3.12
Classifier: Topic :: Scientific/Engineering :: Image Recognition
Classifier: Topic :: Software Development :: Libraries :: Python Modules
Requires-Python: >=3.10
License-File: LICENSE
Requires-Dist: pymupdf>=1.23.0
Requires-Dist: aiohttp>=3.8.0
Requires-Dist: requests>=2.28.0
Requires-Dist: tqdm>=4.65.0
Provides-Extra: dev
Requires-Dist: pytest>=7.4.0; extra == "dev"
Requires-Dist: pytest-asyncio>=0.21.0; extra == "dev"
Requires-Dist: pytest-cov>=4.1.0; extra == "dev"
Requires-Dist: black>=23.0.0; extra == "dev"
Requires-Dist: isort>=5.12.0; extra == "dev"
Requires-Dist: flake8>=6.0.0; extra == "dev"
Requires-Dist: mypy>=1.4.0; extra == "dev"
Requires-Dist: types-requests>=2.28.0; extra == "dev"
Requires-Dist: twine>=4.0.0; extra == "dev"
Dynamic: license-file
